{
  "name": "button-04",
  "type": "registry:block",
  "files": [
    {
      "type": "registry:block",
      "content": "import React from 'react';\r\nimport './Button.css';\r\n\r\nconst Button04 = ({ text = \"Nothing-Plop\" }) => {\r\n  // Define dot indices for the two icon variations\r\n  const firstIconDots = [0, 2, 2, 1, 2, 0, 1, 1, 2, 2, 0, 1, 0, 2, 2, 1, 0, 2, 2, 2, 2, 0, 1, 0, 2];\r\n  const secondIconDots = [0, 2, 2, 1, 2, 0, 1, 1, 2];\r\n\r\n  return (\r\n    <a href=\"#\" className=\"button04 w-inline-block\">\r\n      <span className=\"button04_bg\"></span>\r\n      <span data-text={text} className=\"button04_inner\">\r\n        <span className=\"button04_text\">{text}</span>\r\n        <span className=\"button04_icon-wrap\">\r\n          <span \r\n            style={{ '--index-parent': 0 } as React.CSSProperties} \r\n            className=\"button04_icon\"\r\n          >\r\n            {firstIconDots.map((index, i) => (\r\n              <span\r\n                key={`first-dot-${i}`}\r\n                style={{ '--index': index }as React.CSSProperties}\r\n                className=\"button04_dot\"\r\n              ></span>\r\n            ))}\r\n          </span>\r\n          <span \r\n            style={{ '--index-parent': 1 }as React.CSSProperties} \r\n            className=\"button04_icon is-arrow\"\r\n          >\r\n            {secondIconDots.map((index, i) => (\r\n              <span\r\n                key={`second-dot-${i}`}\r\n                style={{ '--index': index }as React.CSSProperties}\r\n                className=\"button04_dot\"\r\n              ></span>\r\n            ))}\r\n          </span>\r\n        </span>\r\n      </span>\r\n    </a>\r\n  );\r\n};\r\n\r\nexport default Button04;",
      "path": "block/Button/button-04/button.tsx",
      "target": "components/block/Button/button-04/button.tsx"
    },
    {
      "type": "registry:block",
      "content": ".button04 {\r\n  color: #f9f4eb;\r\n  letter-spacing: -.02em;\r\n  text-transform: uppercase;\r\n  -webkit-user-select: none;\r\n  user-select: none;\r\n  transform-style: preserve-3d;\r\n  font-size: .875rem;\r\n  line-height: 1em;\r\n  text-decoration: none;\r\n  display: grid\r\n}\r\n\r\n.button04_bg {\r\n  background-color: #000;\r\n  border-radius: .3125rem;\r\n  grid-area: 1/1;\r\n  overflow: clip\r\n}\r\n\r\n.button04_inner {\r\n  grid-gap: .625rem;\r\n  grid-area: 1/1;\r\n  padding: .875rem .625rem .875rem .75rem;\r\n  display: grid;\r\n  translate: 0\r\n}\r\n\r\n.button04_text {\r\n  grid-area: 1/1\r\n}\r\n\r\n.button04_icon-wrap {\r\n  grid-row: 1;\r\n  display: grid\r\n}\r\n\r\n.button04_icon {\r\n  grid-gap: .0625rem;\r\n  grid-area: 1/1;\r\n  grid-template-columns: 1fr 1fr 1fr 1fr 1fr;\r\n  display: grid\r\n}\r\n\r\n.button04_dot {\r\n  background-color: #f9f4eb;\r\n  border-radius: .0625rem;\r\n  width: .125rem;\r\n  height: .125rem;\r\n  display: block\r\n}\r\n\r\n.button04 {\r\n  --elastic-ease-out: linear(\r\n    0,\r\n    0.5737 7.6%,\r\n    0.8382 11.87%,\r\n    0.9463 14.19%,\r\n    1.0292 16.54%,\r\n    1.0886 18.97%,\r\n    1.1258 21.53%,\r\n    1.137 22.97%,\r\n    1.1424 24.48%,\r\n    1.1423 26.1%,\r\n    1.1366 27.86%,\r\n    1.1165 31.01%,\r\n    1.0507 38.62%,\r\n    1.0219 42.57%,\r\n    0.9995 46.99%,\r\n    0.9872 51.63%,\r\n    0.9842 58.77%,\r\n    1.0011 81.26%,\r\n    1\r\n  );\r\n  --smooth-ease: cubic-bezier(.32, .72, 0, 1);\r\n  --color-ease: cubic-bezier(.215, .61, .355, 1);\r\n  \r\n  transition: transform .45s var(--elastic-ease-out);\r\n  -webkit-tap-highlight-color: transparent;\r\n}\r\n\r\n.button04:active {\r\n\ttransform: scaleX(0.955) scaleY(0.954);\r\n}\r\n\r\n.button04_bg {\r\n\ttransition: scale .45s var(--smooth-ease), background-color .2s var(--color-ease);\r\n}\r\n\r\n.button04_dot {\r\n\ttransition: scale .4s var(--smooth-ease);\r\n  transition-delay: calc(var(--index) * .04s);\r\n}\r\n\r\n.button04_icon.is-arrow .button04_dot {\r\n\tscale: 0;\r\n  transition-delay: 0s;\r\n}\r\n\r\n.button04_text {\r\n\ttransition: scale .45s var(--smooth-ease);\r\n  transform-origin: center top;\r\n}\r\n\r\n.button04_inner::before {\r\n\tcontent: attr(data-text);\r\n  grid-area: 1 / 1;\r\n  scale: 1 0;\r\n  pointer-events: none;\r\n  transition: scale .45s var(--smooth-ease);\r\n  transform-origin: center bottom;\r\n}\r\n\r\n/* dot positioning like an arrow, there is no native nth-child inside Webflow */\r\n.button04_icon.is-arrow .button04_dot:nth-child(1) {\r\n\tgrid-area: 3 / 1;\r\n}\r\n\r\n.button04_icon.is-arrow .button04_dot:nth-child(2) {\r\n\tgrid-area: 3 / 2;\r\n}\r\n\r\n.button04_icon.is-arrow .button04_dot:nth-child(3) {\r\n\tgrid-area: 3 / 3;\r\n}\r\n\r\n.button04_icon.is-arrow .button04_dot:nth-child(4) {\r\n\tgrid-area: 3 / 4;\r\n}\r\n\r\n.button04_icon.is-arrow .button04_dot:nth-child(5) {\r\n\tgrid-area: 3 / 5;\r\n}\r\n\r\n.button04_icon.is-arrow .button04_dot:nth-child(6) {\r\n\tgrid-area: 2 / 4;\r\n}\r\n\r\n.button04_icon.is-arrow .button04_dot:nth-child(7) {\r\n\tgrid-area: 1 / 3;\r\n}\r\n\r\n.button04_icon.is-arrow .button04_dot:nth-child(8) {\r\n\tgrid-area: 4 / 4;\r\n}\r\n\r\n.button04_icon.is-arrow .button04_dot:nth-child(9) {\r\n\tgrid-area: 5 / 3;\r\n}\r\n\r\n@media (hover: hover) and (pointer: fine) {\r\n  .button04:is(:hover, :focus-visible) .button04_text {\r\n  \tscale: 1 0;\r\n  }\r\n  \r\n  .button04:is(:hover, :focus-visible) .button04_inner::before {\r\n  \tscale: 1 1;\r\n  }\r\n  \r\n  .button04:is(:hover, :focus-visible) .button04_dot {\r\n  \tscale: 0;\r\n    transition-delay: calc((var(--index) * .04s) + (var(--index-parent) * .07s));\r\n  }\r\n  \r\n  .button04:is(:hover, :focus-visible) .button04_icon.is-arrow .button04_dot {\r\n  \tscale: 1;\r\n  }\r\n}\r\n\r\n/* style only for touch devices */\r\n@media (hover: none) or (pointer: coarse) {\r\n  .button04:active .button04_bg {\r\n  \tbackground-color: #4D4D4D;\r\n    transition-duration: 0s;\r\n  }\r\n  \r\n  .button04_dot {\r\n  \tscale: 0;\r\n  }\r\n  \r\n  .button04_icon.is-arrow .button04_dot {\r\n  \tscale: 1;\r\n  }\r\n}\r\n",
      "path": "block/Button/button-04/Button.css",
      "target": "components/block/Button/button-04/Button.css"
    }
  ]
}